liblinear_official-2.50.0.dist-info/RECORD
liblinear_official-2.50.0.dist-info/WHEEL
liblinear_official-2.50.0.dist-info/top_level.txt
liblinear_official-2.50.0.dist-info/METADATA
liblinear_official-2.50.0.dist-info/licenses/LICENSE
liblinear/liblinear.py
liblinear/commonutil.py
liblinear/clib.cpython-39-darwin.so
liblinear/__init__.py
liblinear/liblinearutil.py
