Metadata-Version: 2.1
Name: liblinear-official
Version: 2.50.0
Summary: Python binding of LIBLINEAR
Home-page: https://www.csie.ntu.edu.tw/~cjlin/liblinear
Author: ML group @ National Taiwan University
Author-email: cjlin@csie.ntu.edu.tw
License: BSD-3-Clause
License-File: LICENSE
Requires-Dist: scipy
